witchui/__init__.py
witchui/input.py
witchui/printer.py
witchui/selection.py
witchui/text.py
witchui-0.1.0.dist-info/LICENSE
witchui-0.1.0.dist-info/WHEEL
witchui-0.1.0.dist-info/METADATA
witchui-0.1.0.dist-info/RECORD
