Metadata-Version: 2.1
Name: witchui
Version: 0.1.0
Summary: Helpful tools for designing text-based interfaces, based on curses.
Author: Ana Filipe
Author-email: ana.filipe@miniclip.com
Requires-Python: >=3.7,<4.0
Classifier: Programming Language :: Python :: 3
Classifier: Programming Language :: Python :: 3.10
Classifier: Programming Language :: Python :: 3.7
Classifier: Programming Language :: Python :: 3.8
Classifier: Programming Language :: Python :: 3.9
